wagtail_graphql/__init__.py
wagtail_graphql/actions.py
wagtail_graphql/apps.py
wagtail_graphql/permissions.py
wagtail_graphql/registry.py
wagtail_graphql/relay.py
wagtail_graphql/schema.py
wagtail_graphql/settings.py
wagtail_graphql/types/__init__.py
wagtail_graphql/types/auth.py
wagtail_graphql/types/converters.py
wagtail_graphql/types/core.py
wagtail_graphql/types/documents.py
wagtail_graphql/types/forms.py
wagtail_graphql/types/images.py
wagtail_graphql/types/menus.py
wagtail_graphql/types/settings.py
wagtail_graphql/types/snippets.py
wagtail_graphql/types/streamfield.py
wagtail_graphql-0.3.0.dist-info/LICENSE
wagtail_graphql-0.3.0.dist-info/WHEEL
wagtail_graphql-0.3.0.dist-info/METADATA
wagtail_graphql-0.3.0.dist-info/RECORD
