Metadata-Version: 2.1
Name: wagtail-graphql
Version: 0.3.0
Summary: An app to automatically add GraphQL support to a Wagtail website
Home-page: https://github.com/tr11/wagtail-graphql
License: MIT
Keywords: wagtail,graphql,api,wagtail-graphql
Author: Tiago Requeijo
Author-email: tiago.requeijo.dev@gmail.com
Requires-Python: >=3.6,<3.8
Classifier: License :: OSI Approved :: MIT License
Classifier: Programming Language :: Python :: 3
Classifier: Programming Language :: Python :: 3.6
Classifier: Programming Language :: Python :: 3.7
Provides-Extra: menus
Requires-Dist: graphene_django (>=2.2,<3.0)
Requires-Dist: graphene_django_optimizer (>=0.3.5,<0.4.0)
Requires-Dist: python-dateutil (>=2.6,<3.0)
Requires-Dist: wagtail (>=2.3,<3.0)
Requires-Dist: wagtailmenus (>=2.12,<3.0); extra == "menus"
Project-URL: Repository, https://github.com/tr11/wagtail-graphql
